cnb/__init__.py
cnb/core/__init__.py
cnb/core/controllers/__init__.py
cnb/core/controllers/controllers.py
cnb/core/exceptions/__init__.py
cnb/core/exceptions/endpoint_exception.py
cnb/core/models/__init__.py
cnb/core/models/models.py
cnb/core/repositories/__init__.py
cnb/core/repositories/repos.py
cnb/core/schemas/__init__.py
cnb/core/schemas/params.py
cnb/core/schemas/create/__init__.py
cnb/core/schemas/create/schema.py
cnb/core/schemas/response/__init__.py
cnb/core/schemas/response/delete.py
cnb/core/schemas/response/list.py
cnb/core/schemas/response/one.py
cnb/core/schemas/response/remote.py
cnb/core/schemas/update/__init__.py
cnb/core/schemas/update/schema.py
cnb/core/services/__init__.py
cnb/core/services/services.py
cnb/crud/__init__.py
cnb/crud/create.py
cnb/crud/crud.py
cnb/crud/delete.py
cnb/crud/read.py
cnb/crud/update.py
cnb/db/__init__.py
cnb/db/postgres/__init__.py
cnb/db/postgres/create_table.py
cnb/db/postgres/pg_settings.py
cnb/db/postgres/session.py
cnb/dev/__init__.py
cnb/dev/create.py
cnb/dev/create_main.py
cnb/dev/remove.py
cnb/exception/__init__.py
cnb/exception/asgi.py
cnb/exception/handler.py
cnb/log/__init__.py
cnb/log/log_conf.py
cnb/middleware/__init__.py
cnb/middleware/log_request.py
cnb/utils/__init__.py
cnb/utils/sensitive.py
cnb/utils/sensitive_data.py
pyravel/__init__.py
pyravel/cli.py
pyravel/commands/__init__.py
pyravel/commands/base.py
pyravel/commands/generate/__init__.py
pyravel/commands/generate/base.py
pyravel/commands/generate/controller.py
pyravel/commands/generate/docker.py
pyravel/commands/generate/restapi.py
pyravel/commands/generate/service.py
pyravel/commands/init/__init__.py
pyravel/commands/init/base.py
pyravel/utils/__init__.py
pyravel/utils/helper.py
pyravel-0.2.99.dist-info/METADATA
pyravel-0.2.99.dist-info/WHEEL
pyravel-0.2.99.dist-info/entry_points.txt
pyravel-0.2.99.dist-info/top_level.txt
pyravel-0.2.99.dist-info/RECORD
