Metadata-Version: 2.1
Name: pyravel
Version: 0.2.99
Summary: A Python package that builds files from the command line.
Author: Your Name
Author-email: your.email@example.com
Requires-Python: >=3.12
Requires-Dist: questionary
Requires-Dist: rich
Requires-Dist: loguru
